<?xml version="1.0" encoding="UTF-8"?>
<beans xmlns="http://www.springframework.org/schema/beans">
    <!-- Enable support for JPA annotations -->
    <bean class="org.springframework.orm.jpa.support.PersistenceAnnotationBeanPostProcessor"/>

    <!-- Configure a persistence data source bean -->
    <bean id="prod" class="org.springframework.jdbc.datasource.DriverManagerDataSource">
        <property name="driverClassName" value="org.h2.Driver"/>
        <property name="url" value="jdbc:h2:./src/main/resources/db/javabank"/>
        <property name="username" value="sa"/>
        <property name="password" value=""/>
    </bean>

    <!-- Configure an EntityManagerFactory bean -->
    <bean id="emFactory" class="org.springframework.orm.jpa.LocalContainerEntityManagerFactoryBean">
        <property name="dataSource" ref="prod"/>
        <property name="packagesToScan" value="org.academiadecodigo.javabank.model"/>
        <property name="jpaVendorAdapter">
            <bean class="org.springframework.orm.jpa.vendor.HibernateJpaVendorAdapter"/>
        </property>
        <property name="jpaProperties">
            <map>
                <entry key="hibernate.connection.driver_class" value="com.mysql.jdbc.Driver"/>
                <entry key="hibernate.dialect" value="org.hibernate.dialect.MySQL5Dialect"/>
                <entry key="hibernate.connection.url" value="jdbc:mysql://novabase.academiadecodigo.org:3306/ac?useSSL=false"/>
                <entry key="hibernate.connection.username" value="ferrao"/>
                <entry key="hibernate.connection.password" value="ac"/>
                <entry key="hibernate.archive.autodetection" value="class"/>
                <entry key="hibernate.format_sql" value="true"/>
            </map>
        </property>
    </bean>
</beans>